pyfttt/__init__.py
pyfttt/cmd_script.py
pyfttt/sending.py
pyfttt/server.py
pyfttt/test_server.py
pyfttt-0.3.2.dist-info/DESCRIPTION.rst
pyfttt-0.3.2.dist-info/METADATA
pyfttt-0.3.2.dist-info/RECORD
pyfttt-0.3.2.dist-info/WHEEL
pyfttt-0.3.2.dist-info/entry_points.txt
pyfttt-0.3.2.dist-info/metadata.json
pyfttt-0.3.2.dist-info/top_level.txt
