Metadata-Version: 2.0
Name: pyfttt
Version: 0.3.2
Summary: Python tools for interacting with the IFTTT Webhooks Channel
Home-page: https://github.com/briandconnelly/pyfttt
Author: Brian Connelly
Author-email: bdc@bconnelly.net
License: BSD
Keywords: IFTTT automation
Platform: UNKNOWN
Classifier: Development Status :: 4 - Beta
Classifier: Intended Audience :: End Users/Desktop
Classifier: License :: OSI Approved :: BSD License
Classifier: Programming Language :: Python :: 2.7
Classifier: Programming Language :: Python :: 3.4
Classifier: Programming Language :: Python :: 3.5
Classifier: Programming Language :: Python :: 3.6
Requires-Dist: requests (>=2.7)
